southerncross/__init__.py
southerncross/flask.py
southerncross/gunicorn.py
southerncross/jsonschema.py
southerncross/jwt.py
southerncross/mail.py
southerncross/requests_unixsocket.py
southerncross/utils.py
southerncross/validators.py
southerncross/i18n/__init__.py
southerncross/i18n/default_dictionary.py
southerncross/sqlalchemy/__init__.py
southerncross/sqlalchemy/types.py
southerncross/testing/utils.py
southerncross/wtforms/__init__.py
southerncross/wtforms/validators.py
southerncross-0.8.7.dist-info/LICENSE
southerncross-0.8.7.dist-info/METADATA
southerncross-0.8.7.dist-info/WHEEL
southerncross-0.8.7.dist-info/top_level.txt
southerncross-0.8.7.dist-info/RECORD
