Metadata-Version: 2.1
Name: southerncross
Version: 0.8.7
Summary: Provides common frameworks using flask, wtforms, gunicorn and sqlalchemy.
License: Unlicense
Platform: any
Classifier: Environment :: Web Environment
Classifier: License :: OSI Approved :: The Unlicense (Unlicense)
Classifier: Programming Language :: Python
Classifier: Programming Language :: Python :: 3
Classifier: Programming Language :: Python :: 3.10
Classifier: Programming Language :: Python :: 3.11
Classifier: Programming Language :: Python :: 3.12
Classifier: Programming Language :: Python :: 3.13
Classifier: Programming Language :: Python :: 3.14
License-File: LICENSE
Requires-Dist: flask>=2.2.0
Requires-Dist: sqlalchemy>=1.4.0
Requires-Dist: gunicorn
Requires-Dist: requests
